README.md
setup.py
jsonsible/__init__.py
jsonsible/jsonsible.py
jsonsible.egg-info/PKG-INFO
jsonsible.egg-info/SOURCES.txt
jsonsible.egg-info/dependency_links.txt
jsonsible.egg-info/top_level.txt
jsonsible/test/__init__.py
jsonsible/test/jsonsible_create_test.py